jcell/__init__.py
jcell/main.py
jcell/tets.py
jcell/update.py
jcell/.vscode/launch.json
jcell/.vscode/settings.json
jcell/.vscode/tasks.json
jcell/dataset_utils/__init__.py
jcell/dataset_utils/data_proc.py
jcell/dataset_utils/imageutl.py
jcell/dataset_utils/proc2d/__init__.py
jcell/dataset_utils/proc2d/augmentation.py
jcell/dataset_utils/proc2d/inst2sem.py
jcell/dataset_utils/proc3d/__init__.py
jcell/dataset_utils/proc3d/augmentation.py
jcell/dataset_utils/proc3d/inst2sem.py
jcell/evaluation/__init__.py
jcell/evaluation/run.py
jcell/evaluation/src/__init__.py
jcell/evaluation/src/iou_mat.py
jcell/evaluation/src/test.py
jcell/evaluation/src/dataloaders/__init__.py
jcell/evaluation/src/dataloaders/imageutl.py
jcell/evaluation/src/dataloaders/segdataset/__init__.py
jcell/evaluation/src/dataloaders/segdataset/ctransforms.py
jcell/evaluation/src/models/__init__.py
jcell/evaluation/src/models/unet.py
jcell/evaluation/src/models/unet3pad.py
jcell/evaluation/src/models/unet3pad3.py
jcell/evaluation/src/models/unetpad.py
jcell/evaluation/src/post/__init__.py
jcell/evaluation/src/post/post_processing_func.py
jcell/evaluation/src/utils/__init__.py
jcell/evaluation/src/utils/utils.py
jcell/evaluation/src/utils/visualization.py
jcell/train/__init__.py
jcell/train/src/__init__.py
jcell/train/src/train.py
jcell/train/src/dataloaders/__init__.py
jcell/train/src/dataloaders/segdataset/__init__.py
jcell/train/src/dataloaders/segdataset/ctransforms.py
jcell/train/src/dataloaders/segdataset/dataset.py
jcell/train/src/dataloaders/segdataset/grid_sample.py
jcell/train/src/dataloaders/segdataset/tps_grid_gen.py
jcell/train/src/dataloaders/segdataset_all/__init__.py
jcell/train/src/dataloaders/segdataset_all/ctransforms.py
jcell/train/src/dataloaders/segdataset_all/dataset.py
jcell/train/src/dataloaders/segdataset_all/grid_sample.py
jcell/train/src/dataloaders/segdataset_all/tps_grid_gen.py
jcell/train/src/defaults/dataconfig_dev.json
jcell/train/src/defaults/dataconfig_train.json
jcell_ISBI-0.0.1a4.dist-info/LICENSE
jcell_ISBI-0.0.1a4.dist-info/METADATA
jcell_ISBI-0.0.1a4.dist-info/WHEEL
jcell_ISBI-0.0.1a4.dist-info/top_level.txt
jcell_ISBI-0.0.1a4.dist-info/RECORD
