Metadata-Version: 2.1
Name: jcell_ISBI
Version: 0.0.1a4
Summary: Software package for training and testing deep learning based method applied to image segmentation
Home-page: http://jcell.org
Author: Fidel Guerrero Pena
Author-email: fagp@cin.ufpe.br
License: UNKNOWN
Platform: UNKNOWN
Classifier: Programming Language :: Python :: 3
Classifier: License :: OSI Approved :: MIT License
Classifier: Operating System :: POSIX :: Linux
Requires-Python: >=3.6
Requires-Dist: numpy
Requires-Dist: Pillow
Requires-Dist: scikit-image
Requires-Dist: scipy
Requires-Dist: torch (>=1.7.1)
Requires-Dist: torchvision (>=0.8.2)
Requires-Dist: visdom (>=0.1.8.9)
Requires-Dist: numba
Requires-Dist: llc
Requires-Dist: imageio
Requires-Dist: imagecodecs
Requires-Dist: wget
Requires-Dist: requests
Requires-Dist: tqdm
